geoevolve/__init__.py
geoevolve/_version.py
geoevolve/api.py
geoevolve/code_evolver.py
geoevolve/config.py
geoevolve/geo_knowledge_rag.py
geoevolve/llm.py
geoevolve/prompt_generator.py
geoevolve/utils.py
geoevolve-0.2.6.dist-info/licenses/LICENSE
geoevolve-0.2.6.dist-info/METADATA
geoevolve-0.2.6.dist-info/WHEEL
geoevolve-0.2.6.dist-info/top_level.txt
geoevolve-0.2.6.dist-info/RECORD
