Metadata-Version: 2.4
Name: geoevolve
Version: 0.2.6
Summary: A Geographical Knowledge Informed Code Evolver
Author-email: Xiayin Lou <xiayin.lou@tum.de>
License-Expression: MIT
Keywords: Large Language Models,Geospatial Artificial Intelligence,Knowledge Discovery
Requires-Python: >=3.10
License-File: LICENSE
Requires-Dist: arxiv>=2.3.1
Requires-Dist: gitpython>=3.1.45
Requires-Dist: langchain>=1.1.0
Requires-Dist: langchain-chroma>=1.0.0
Requires-Dist: langchain-community>=0.4.1
Requires-Dist: langchain-core>=1.1.0
Requires-Dist: langchain-openai>=1.1.0
Requires-Dist: langgraph>=1.0.4
Requires-Dist: more-itertools>=10.8.0
Requires-Dist: openevolve>=0.2.22
Requires-Dist: pymupdf>=1.26.6
Requires-Dist: requests>=2.32.5
Requires-Dist: ruamel-yaml>=0.18.16
Requires-Dist: tqdm>=4.67.1
Requires-Dist: wikipedia-api>=0.8.1
Dynamic: license-file
